Metadata-Version: 1.1
Name: waters
Version: 0.0.4
Summary: Parsing MS data from Waters.
Home-page: https://github.com/MatteoLacki/waters/
Author: Mateusz Krzysztof Łącki
Author-email: matteo.lacki@gmail.com
License: UNKNOWN
Keywords: Mass Spectrometry,Waters
Platform: UNKNOWN
Classifier: Development Status :: 1 - Planning
Classifier: License :: OSI Approved :: BSD License
Classifier: Intended Audience :: Science/Research
Classifier: Topic :: Scientific/Engineering :: Chemistry
Classifier: Programming Language :: Python :: 3.7
